<?xml version="1.0" encoding="UTF-8"?>
<databases>
    <database>
        <metaInformations>
            <dbName>Db1</dbName>
            <creatorName>roman</creatorName>
            <creationDate>24/10/2013</creationDate>
        </metaInformations>
        <tables>
            <table>
                <name>Table1</name>
                <columns>
                    <column>
                        <name>Col1</name>
                        <type>int</type>
                    </column>
                    <column>
                        <name>Col2</name>
                        <type>string</type>
                    </column>
                    <column>
                        <name>Col3</name>
                        <type>text</type>
                    </column>
                </columns>
                <primaryKey>Col1</primaryKey>
            </table>
            <table>
                <name>Table2</name>
                <columns>
                    <column>
                        <name>Col1</name>
                        <type>int</type>
                    </column>
                    <column>
                        <name>Col2</name>
                        <type>string</type>
                    </column>
                </columns>
                <primaryKey>Col1</primaryKey>
            </table>
        </tables>
    </database>
</databases>
